syntaxsemanticanalysis/__init__.py
syntaxsemanticanalysis/cli.py
syntaxsemanticanalysis/syntaxsemanticanalysis.py
syntaxsemanticanalysis-0.1.0.dist-info/DESCRIPTION.rst
syntaxsemanticanalysis-0.1.0.dist-info/METADATA
syntaxsemanticanalysis-0.1.0.dist-info/RECORD
syntaxsemanticanalysis-0.1.0.dist-info/WHEEL
syntaxsemanticanalysis-0.1.0.dist-info/entry_points.txt
syntaxsemanticanalysis-0.1.0.dist-info/metadata.json
syntaxsemanticanalysis-0.1.0.dist-info/top_level.txt
