Metadata-Version: 2.0
Name: syntaxsemanticanalysis
Version: 0.1.0
Summary: Syntactic and Semantic Evolution for long-standing Texts
Home-page: https://github.com/javierobledo/syntaxsemanticanalysis
Author: Javier Robledo
Author-email: javier.robledo@usm.cl
License: MIT license
Keywords: syntaxsemanticanalysis
Platform: UNKNOWN
Classifier: Development Status :: 2 - Pre-Alpha
Classifier: Intended Audience :: Developers
Classifier: License :: OSI Approved :: MIT License
Classifier: Natural Language :: English
Classifier: Programming Language :: Python :: 2
Classifier: Programming Language :: Python :: 2.6
Classifier: Programming Language :: Python :: 2.7
Classifier: Programming Language :: Python :: 3
Classifier: Programming Language :: Python :: 3.3
Classifier: Programming Language :: Python :: 3.4
Classifier: Programming Language :: Python :: 3.5
Requires-Dist: Click (>=6.0)
